kuwahara_torch/__init__.py
kuwahara_torch/functional.py
kuwahara_torch/ops.py
kuwahara_torch/utils.py
kuwahara_torch-0.0.3.dist-info/LICENSE
kuwahara_torch-0.0.3.dist-info/METADATA
kuwahara_torch-0.0.3.dist-info/WHEEL
kuwahara_torch-0.0.3.dist-info/top_level.txt
kuwahara_torch-0.0.3.dist-info/RECORD
