Metadata-Version: 2.1
Name: kuwahara-torch
Version: 0.0.3
Summary: Kuwahara filter in PyTorch.
Author-email: Evan Arlian <evanarlian2000@gmail.com>
License: MIT License
Project-URL: Homepage, https://github.com/evanarlian/kuwahara-torch
Keywords: pytorch,shaders,image,kuwahara
Classifier: Programming Language :: Python :: 3
Classifier: License :: OSI Approved :: MIT License
Classifier: Operating System :: OS Independent
Requires-Python: >=3.10
License-File: LICENSE
Requires-Dist: torch
Requires-Dist: numpy
Requires-Dist: Pillow
